panoptes_aggregation/__init__.py
panoptes_aggregation/append_version.py
panoptes_aggregation/batch_aggregation.py
panoptes_aggregation/copy_function.py
panoptes_aggregation/csv_utils.py
panoptes_aggregation/feedback_strategies.py
panoptes_aggregation/routes.py
panoptes_aggregation/shape_tools.py
panoptes_aggregation/workflow_config.py
panoptes_aggregation/extractors/__init__.py
panoptes_aggregation/extractors/all_tasks_empty_extractor.py
panoptes_aggregation/extractors/bezier_extractor.py
panoptes_aggregation/extractors/dropdown_extractor.py
panoptes_aggregation/extractors/extractor_wrapper.py
panoptes_aggregation/extractors/i2a_extractor.py
panoptes_aggregation/extractors/line_text_extractor.py
panoptes_aggregation/extractors/nfn_extractor.py
panoptes_aggregation/extractors/point_extractor.py
panoptes_aggregation/extractors/point_extractor_by_frame.py
panoptes_aggregation/extractors/poly_line_text_extractor.py
panoptes_aggregation/extractors/polygon_extractor.py
panoptes_aggregation/extractors/question_extractor.py
panoptes_aggregation/extractors/rectangle_extractor.py
panoptes_aggregation/extractors/shape_extractor.py
panoptes_aggregation/extractors/slider_extractor.py
panoptes_aggregation/extractors/subtask_extractor_wrapper.py
panoptes_aggregation/extractors/survey_extractor.py
panoptes_aggregation/extractors/sw_extractor.py
panoptes_aggregation/extractors/sw_graphic_extractor.py
panoptes_aggregation/extractors/sw_variant_extractor.py
panoptes_aggregation/extractors/text_extractor.py
panoptes_aggregation/extractors/tool_wrapper.py
panoptes_aggregation/extractors/utilities.py
panoptes_aggregation/panoptes/__init__.py
panoptes_aggregation/panoptes/userify.py
panoptes_aggregation/reducers/__init__.py
panoptes_aggregation/reducers/dropdown_reducer.py
panoptes_aggregation/reducers/first_n_false_reducer.py
panoptes_aggregation/reducers/first_n_true_reducer.py
panoptes_aggregation/reducers/optics_line_text_reducer.py
panoptes_aggregation/reducers/optics_text_utils.py
panoptes_aggregation-5.3.0.dist-info/entry_points.txt
panoptes_aggregation-5.3.0.dist-info/licenses/LICENSE
panoptes_aggregation-5.3.0.dist-info/WHEEL
panoptes_aggregation-5.3.0.dist-info/METADATA
panoptes_aggregation-5.3.0.dist-info/RECORD
