Metadata-Version: 2.4
Name: panoptes_aggregation
Version: 5.3.0
Summary: Aggregation code for Zooniverse panoptes projects.
Author-email: Coleman Krawczyk <coleman@zooniverse.org>
Requires-Python: >=3.9,<3.14
Classifier: Programming Language :: Python :: 3 :: Only
Classifier: License :: OSI Approved :: Apache Software License
License-File: LICENSE
Requires-Dist: beautifulsoup4>=4.8.1,<4.13
Requires-Dist: collatex>=2.3,<2.4
Requires-Dist: lxml>=4.4,<5.4
Requires-Dist: numpy>=1.26.4,<2.3
Requires-Dist: packaging>=20.1,<24.3
Requires-Dist: pandas>=2.0
Requires-Dist: progressbar2>=3.39,<4.6
Requires-Dist: python-levenshtein>=0.21.0,<0.27
Requires-Dist: python-slugify>=7.0.0,<8.1
Requires-Dist: pyyaml>=6.0,<6.1
Requires-Dist: scikit-learn>=1.3.2,<1.7
Requires-Dist: scipy>=1.10.0
Requires-Dist: werkzeug>=2.3.0,<3.2
Requires-Dist: shapely>=2.0,<2.1
Requires-Dist: contourpy>=1.3.0,<1.4.0
Requires-Dist: shapelysmooth>=0.2.0,<1.0
Requires-Dist: matplotlib>=3.5.1,<4.0 ; extra == "doc"
Requires-Dist: myst-nb>=0.13.2,<2.0 ; extra == "doc"
Requires-Dist: sphinx>=5.2.0,<7.5 ; extra == "doc"
Requires-Dist: sphinxcontrib-httpdomain>=1.7.0,<1.9 ; extra == "doc"
Requires-Dist: sphinx_rtd_theme>=0.4.3,<4.0 ; extra == "doc"
Requires-Dist: Gooey>=1.0.8.1,<1.1 ; extra == "gui"
Requires-Dist: pip-licenses>=5.0 ; extra == "installer"
Requires-Dist: nuitka>=2.6.8 ; extra == "installer"
Requires-Dist: azure-identity>=1,<2 ; extra == "online"
Requires-Dist: azure-storage-blob>=12,<13 ; extra == "online"
Requires-Dist: celery>=5.3,<5.5 ; extra == "online"
Requires-Dist: redis>=5,<6 ; extra == "online"
Requires-Dist: flower>2,<3 ; extra == "online"
Requires-Dist: flask>=2.3,<3.2 ; extra == "online"
Requires-Dist: flask-cors>=3.0,<5.1 ; extra == "online"
Requires-Dist: panoptes-client>=1.6,<1.7 ; extra == "online"
Requires-Dist: requests>=2.28,<2.33 ; extra == "online"
Requires-Dist: gunicorn>=20.0,<24.0 ; extra == "online"
Requires-Dist: sentry-sdk[flask]>=2.19,<2.20 ; extra == "online"
Requires-Dist: setuptools>=75.8,<76.0 ; extra == "online"
Requires-Dist: standard-imghdr>=3.13,<4.0 ; extra == "online"
Requires-Dist: newrelic>=8.4.0,<10.4 ; extra == "online"
Requires-Dist: gitpython>=3.0.0,<3.2 ; extra == "online"
Requires-Dist: coverage>=4.5.3,<7.7 ; extra == "test"
Requires-Dist: coveralls>=3.0.0,<4.1 ; extra == "test"
Requires-Dist: flake8>=7.0,<7.2 ; extra == "test"
Requires-Dist: flake8-black>=0.3.4,<0.4 ; extra == "test"
Requires-Dist: flake8-bugbear>=23.5,<24.11 ; extra == "test"
Requires-Dist: pytest>=7.1.2,<8.4 ; extra == "test"
Requires-Dist: pytest-subtests>=0.10.0,<0.14 ; extra == "test"
Project-URL: Documentation, https://aggregation-caesar.zooniverse.org/docs
Project-URL: Source, https://github.com/zooniverse/aggregation-for-caesar
Provides-Extra: doc
Provides-Extra: gui
Provides-Extra: installer
Provides-Extra: online
Provides-Extra: test
